icarus/projects/mini_computer/8bit_cpu/logic_gates/gates.sv
// NAND GATE
module nand_gate(
  input wire a,
  input wire b,
  output wire y
);

  assign y = ~(a & b);

endmodule

// NOT GATE
module not_gate(
  input wire a,
  output wire y
);

  nand_gate nand1(
    .a(a),
    .b(a),
    .y(y)
  );

endmodule

// AND GATE
module and_gate(
  input wire a,
  input wire b,
  output wire y
);

  wire nand_out;

  nand_gate nand1(
    .a(a),
    .b(b),
    .y(nand_out)
  );

  not_gate not1(
    .a(nand_out),
    .y(y)
  );

endmodule

// OR GATE
module or_gate(
  input wire a,  
  input wire b,  
  output wire y 
);

  wire not_out1;
  wire not_out2;

  not_gate not1(
    .a(a),    
    .y(not_out1)
  );

  not_gate not2(
    .a(b),    
    .y(not_out2)
  );

  nand_gate nand1(
    .a(not_out1),
    .b(not_out2),
    .y(y)
  );

endmodule

// NOR GATE
module nor_gate(
  input wire a,
  input wire b,
  output wire y
);

  wire or_out;

  or_gate or1(
    .a(a),
    .b(b),
    .y(or_out)
  );

  
  not_gate not1(
    .a(or_out),
    .y(y)
  );

endmodule

// XOR GATE
module xor_gate(
  input wire a,
  input wire b,
  output wire y
);

  wire not_a;
  wire not_b;

  not_gate not1(
    .a(a),
    .y(not_a)
  );

  not_gate not2(
    .a(b),
    .y(not_b)
  );

  wire and_out1;
  wire and_out2;

  and_gate and1(
    .a(not_a),  
    .b(b),
    .y(and_out1)
  );

  and_gate and2(
    .a(a),  
    .b(not_b),
    .y(and_out2)
  );

  or_gate or1(
    .a(and_out1),
    .b(and_out2),
    .y(y)
  );

endmodule

// XNOR GATE
module xnor_gate(
  input wire a,
  input wire b,
  output wire y
);

  wire xor_out;

  xor_gate xor1(
    .a(a),
    .b(b),
    .y(xor_out)
  );

  not_gate not1(
    .a(xor_out),
    .y(y)
  );

endmodule

icarus/projects/mini_computer/8bit_cpu/adders/adders.sv
// HALF ADDER
module half_adder(
  input wire a,
  input wire b,

  output wire sum,
  output wire carry
);

  xor_gate xor1(
    .a(a),
    .b(b),
    .y(sum)
  );

  and_gate and1(
    .a(a),
    .b(b),
    .y(carry)
  );

endmodule

// FULL ADDER
module full_adder(
  input wire a,
  input wire b,
  input wire cin,

  output wire sum,
  output wire carry
);

  wire h1_sum;
  wire h1_carry;
  wire h2_carry;

  half_adder h1(
    .a(a),
    .b(b),
    .sum(h1_sum),
    .carry(h1_carry)
  );

  half_adder h2(
    .a(h1_sum),
    .b(cin),
    .sum(sum),
    .carry(h2_carry)
  );

  or_gate or1(
    .a(h1_carry),
    .b(h2_carry),
    .y(carry)
  );

endmodule

icarus/projects/mini_computer/8bit_cpu/adders/tb_adders.sv
module tb_adders;

  reg a;
  reg b;
  reg cin;

  wire ha_sum;
  wire ha_carry;

  wire fa_sum;
  wire fa_carry;

  half_adder ha(
    .a(a),
    .b(b),
    .sum(ha_sum),
    .carry(ha_carry)
  );

  full_adder fa(
    .a(a),
    .b(b),
    .cin(cin),
    .sum(fa_sum),
    .carry(fa_carry)
  );

  initial begin
    $dumpfile("adders_wf.vcd");
    $dumpvars(0, tb_adders);

    $monitor("A=%b, B=%b, CIN=%b | HA_SUM=%b, HA_CARRY=%b, FA_SUM=%b, FA_CARRY=%b", a, b, cin, ha_sum, ha_carry, fa_sum, fa_carry);

    a=0; b=0; cin=0; #10;
    a=0; b=0; cin=1; #10;
    a=0; b=1; cin=0; #10;
    a=0; b=1; cin=1; #10;
    a=1; b=0; cin=0; #10;
    a=1; b=0; cin=1; #10;
    a=1; b=1; cin=0; #10;
    a=1; b=1; cin=1; #10;
  
    $finish;
  end

endmodule

icarus/projects/mini_computer/8bit_cpu/adders/adders_wf.vcd
$date
	Fri Sep 25 13:09:15 2026
$end
$version
	Icarus Verilog
$end
$timescale
	1s
$end
$scope module tb_adders $end
$var wire 1 ! ha_sum $end
$var wire 1 " ha_carry $end
$var wire 1 # fa_sum $end
$var wire 1 $ fa_carry $end
$var reg 1 % a $end
$var reg 1 & b $end
$var reg 1 ' cin $end
$scope module fa $end
$var wire 1 % a $end
$var wire 1 & b $end
$var wire 1 ' cin $end
$var wire 1 # sum $end
$var wire 1 ( h2_carry $end
$var wire 1 ) h1_sum $end
$var wire 1 * h1_carry $end
$var wire 1 $ carry $end
$scope module h1 $end
$var wire 1 % a $end
$var wire 1 & b $end
$var wire 1 ) sum $end
$var wire 1 * carry $end
$scope module and1 $end
$var wire 1 % a $end
$var wire 1 & b $end
$var wire 1 * y $end
$var wire 1 + nand_out $end
$scope module nand1 $end
$var wire 1 % a $end
$var wire 1 & b $end
$var wire 1 + y $end
$upscope $end
$scope module not1 $end
$var wire 1 + a $end
$var wire 1 * y $end
$scope module nand1 $end
$var wire 1 + a $end
$var wire 1 + b $end
$var wire 1 * y $end
$upscope $end
$upscope $end
$upscope $end
$scope module xor1 $end
$var wire 1 % a $end
$var wire 1 & b $end
$var wire 1 ) y $end
$var wire 1 , not_b $end
$var wire 1 - not_a $end
$var wire 1 . and_out2 $end
$var wire 1 / and_out1 $end
$scope module and1 $end
$var wire 1 & b $end
$var wire 1 / y $end
$var wire 1 0 nand_out $end
$var wire 1 - a $end
$scope module nand1 $end
$var wire 1 & b $end
$var wire 1 0 y $end
$var wire 1 - a $end
$upscope $end
$scope module not1 $end
$var wire 1 0 a $end
$var wire 1 / y $end
$scope module nand1 $end
$var wire 1 0 a $end
$var wire 1 0 b $end
$var wire 1 / y $end
$upscope $end
$upscope $end
$upscope $end
$scope module and2 $end
$var wire 1 % a $end
$var wire 1 . y $end
$var wire 1 1 nand_out $end
$var wire 1 , b $end
$scope module nand1 $end
$var wire 1 % a $end
$var wire 1 1 y $end
$var wire 1 , b $end
$upscope $end
$scope module not1 $end
$var wire 1 1 a $end
$var wire 1 . y $end
$scope module nand1 $end
$var wire 1 1 a $end
$var wire 1 1 b $end
$var wire 1 . y $end
$upscope $end
$upscope $end
$upscope $end
$scope module not1 $end
$var wire 1 % a $end
$var wire 1 - y $end
$scope module nand1 $end
$var wire 1 % a $end
$var wire 1 % b $end
$var wire 1 - y $end
$upscope $end
$upscope $end
$scope module not2 $end
$var wire 1 & a $end
$var wire 1 , y $end
$scope module nand1 $end
$var wire 1 & a $end
$var wire 1 & b $end
$var wire 1 , y $end
$upscope $end
$upscope $end
$scope module or1 $end
$var wire 1 / a $end
$var wire 1 . b $end
$var wire 1 ) y $end
$var wire 1 2 not_out2 $end
$var wire 1 3 not_out1 $end
$scope module nand1 $end
$var wire 1 ) y $end
$var wire 1 2 b $end
$var wire 1 3 a $end
$upscope $end
$scope module not1 $end
$var wire 1 / a $end
$var wire 1 3 y $end
$scope module nand1 $end
$var wire 1 / a $end
$var wire 1 / b $end
$var wire 1 3 y $end
$upscope $end
$upscope $end
$scope module not2 $end
$var wire 1 . a $end
$var wire 1 2 y $end
$scope module nand1 $end
$var wire 1 . a $end
$var wire 1 . b $end
$var wire 1 2 y $end
$upscope $end
$upscope $end
$upscope $end
$upscope $end
$upscope $end
$scope module h2 $end
$var wire 1 ) a $end
$var wire 1 ' b $end
$var wire 1 # sum $end
$var wire 1 ( carry $end
$scope module and1 $end
$var wire 1 ) a $end
$var wire 1 ' b $end
$var wire 1 ( y $end
$var wire 1 4 nand_out $end
$scope module nand1 $end
$var wire 1 ) a $end
$var wire 1 ' b $end
$var wire 1 4 y $end
$upscope $end
$scope module not1 $end
$var wire 1 4 a $end
$var wire 1 ( y $end
$scope module nand1 $end
$var wire 1 4 a $end
$var wire 1 4 b $end
$var wire 1 ( y $end
$upscope $end
$upscope $end
$upscope $end
$scope module xor1 $end
$var wire 1 ) a $end
$var wire 1 ' b $end
$var wire 1 # y $end
$var wire 1 5 not_b $end
$var wire 1 6 not_a $end
$var wire 1 7 and_out2 $end
$var wire 1 8 and_out1 $end
$scope module and1 $end
$var wire 1 ' b $end
$var wire 1 8 y $end
$var wire 1 9 nand_out $end
$var wire 1 6 a $end
$scope module nand1 $end
$var wire 1 ' b $end
$var wire 1 9 y $end
$var wire 1 6 a $end
$upscope $end
$scope module not1 $end
$var wire 1 9 a $end
$var wire 1 8 y $end
$scope module nand1 $end
$var wire 1 9 a $end
$var wire 1 9 b $end
$var wire 1 8 y $end
$upscope $end
$upscope $end
$upscope $end
$scope module and2 $end
$var wire 1 ) a $end
$var wire 1 7 y $end
$var wire 1 : nand_out $end
$var wire 1 5 b $end
$scope module nand1 $end
$var wire 1 ) a $end
$var wire 1 : y $end
$var wire 1 5 b $end
$upscope $end
$scope module not1 $end
$var wire 1 : a $end
$var wire 1 7 y $end
$scope module nand1 $end
$var wire 1 : a $end
$var wire 1 : b $end
$var wire 1 7 y $end
$upscope $end
$upscope $end
$upscope $end
$scope module not1 $end
$var wire 1 ) a $end
$var wire 1 6 y $end
$scope module nand1 $end
$var wire 1 ) a $end
$var wire 1 ) b $end
$var wire 1 6 y $end
$upscope $end
$upscope $end
$scope module not2 $end
$var wire 1 ' a $end
$var wire 1 5 y $end
$scope module nand1 $end
$var wire 1 ' a $end
$var wire 1 ' b $end
$var wire 1 5 y $end
$upscope $end
$upscope $end
$scope module or1 $end
$var wire 1 8 a $end
$var wire 1 7 b $end
$var wire 1 # y $end
$var wire 1 ; not_out2 $end
$var wire 1 < not_out1 $end
$scope module nand1 $end
$var wire 1 # y $end
$var wire 1 ; b $end
$var wire 1 < a $end
$upscope $end
$scope module not1 $end
$var wire 1 8 a $end
$var wire 1 < y $end
$scope module nand1 $end
$var wire 1 8 a $end
$var wire 1 8 b $end
$var wire 1 < y $end
$upscope $end
$upscope $end
$scope module not2 $end
$var wire 1 7 a $end
$var wire 1 ; y $end
$scope module nand1 $end
$var wire 1 7 a $end
$var wire 1 7 b $end
$var wire 1 ; y $end
$upscope $end
$upscope $end
$upscope $end
$upscope $end
$upscope $end
$scope module or1 $end
$var wire 1 * a $end
$var wire 1 ( b $end
$var wire 1 $ y $end
$var wire 1 = not_out2 $end
$var wire 1 > not_out1 $end
$scope module nand1 $end
$var wire 1 $ y $end
$var wire 1 = b $end
$var wire 1 > a $end
$upscope $end
$scope module not1 $end
$var wire 1 * a $end
$var wire 1 > y $end
$scope module nand1 $end
$var wire 1 * a $end
$var wire 1 * b $end
$var wire 1 > y $end
$upscope $end
$upscope $end
$scope module not2 $end
$var wire 1 ( a $end
$var wire 1 = y $end
$scope module nand1 $end
$var wire 1 ( a $end
$var wire 1 ( b $end
$var wire 1 = y $end
$upscope $end
$upscope $end
$upscope $end
$upscope $end
$scope module ha $end
$var wire 1 % a $end
$var wire 1 & b $end
$var wire 1 ! sum $end
$var wire 1 " carry $end
$scope module and1 $end
$var wire 1 % a $end
$var wire 1 & b $end
$var wire 1 " y $end
$var wire 1 ? nand_out $end
$scope module nand1 $end
$var wire 1 % a $end
$var wire 1 & b $end
$var wire 1 ? y $end
$upscope $end
$scope module not1 $end
$var wire 1 ? a $end
$var wire 1 " y $end
$scope module nand1 $end
$var wire 1 ? a $end
$var wire 1 ? b $end
$var wire 1 " y $end
$upscope $end
$upscope $end
$upscope $end
$scope module xor1 $end
$var wire 1 % a $end
$var wire 1 & b $end
$var wire 1 ! y $end
$var wire 1 @ not_b $end
$var wire 1 A not_a $end
$var wire 1 B and_out2 $end
$var wire 1 C and_out1 $end
$scope module and1 $end
$var wire 1 & b $end
$var wire 1 C y $end
$var wire 1 D nand_out $end
$var wire 1 A a $end
$scope module nand1 $end
$var wire 1 & b $end
$var wire 1 D y $end
$var wire 1 A a $end
$upscope $end
$scope module not1 $end
$var wire 1 D a $end
$var wire 1 C y $end
$scope module nand1 $end
$var wire 1 D a $end
$var wire 1 D b $end
$var wire 1 C y $end
$upscope $end
$upscope $end
$upscope $end
$scope module and2 $end
$var wire 1 % a $end
$var wire 1 B y $end
$var wire 1 E nand_out $end
$var wire 1 @ b $end
$scope module nand1 $end
$var wire 1 % a $end
$var wire 1 E y $end
$var wire 1 @ b $end
$upscope $end
$scope module not1 $end
$var wire 1 E a $end
$var wire 1 B y $end
$scope module nand1 $end
$var wire 1 E a $end
$var wire 1 E b $end
$var wire 1 B y $end
$upscope $end
$upscope $end
$upscope $end
$scope module not1 $end
$var wire 1 % a $end
$var wire 1 A y $end
$scope module nand1 $end
$var wire 1 % a $end
$var wire 1 % b $end
$var wire 1 A y $end
$upscope $end
$upscope $end
$scope module not2 $end
$var wire 1 & a $end
$var wire 1 @ y $end
$scope module nand1 $end
$var wire 1 & a $end
$var wire 1 & b $end
$var wire 1 @ y $end
$upscope $end
$upscope $end
$scope module or1 $end
$var wire 1 C a $end
$var wire 1 B b $end
$var wire 1 ! y $end
$var wire 1 F not_out2 $end
$var wire 1 G not_out1 $end
$scope module nand1 $end
$var wire 1 ! y $end
$var wire 1 F b $end
$var wire 1 G a $end
$upscope $end
$scope module not1 $end
$var wire 1 C a $end
$var wire 1 G y $end
$scope module nand1 $end
$var wire 1 C a $end
$var wire 1 C b $end
$var wire 1 G y $end
$upscope $end
$upscope $end
$scope module not2 $end
$var wire 1 B a $end
$var wire 1 F y $end
$scope module nand1 $end
$var wire 1 B a $end
$var wire 1 B b $end
$var wire 1 F y $end
$upscope $end
$upscope $end
$upscope $end
$upscope $end
$upscope $end
$upscope $end
$enddefinitions $end
$comment Show the parameter values. $end
$dumpall
$end
#0
$dumpvars
1G
1F
1E
1D
0C
0B
1A
1@
1?
1>
1=
1<
1;
1:
19
08
07
16
15
14
13
12
11
10
0/
0.
1-
1,
1+
0*
0)
0(
0'
0&
0%
0$
0#
0"
0!
$end
#10
1#
0<
18
09
05
1'
#20
0;
17
0:
06
1#
1)
1!
1<
03
0G
08
1/
1C
19
15
00
0,
0D
0@
0'
1&
#30
0#
1$
1;
0=
07
1(
1:
04
05
1'
#40
1#
06
0$
0;
1)
02
1!
0F
1=
17
13
1.
1G
1B
0(
0:
0/
01
0C
0E
14
15
10
1,
1D
1@
0-
0A
0'
0&
1%
#50
0#
1$
1;
0=
07
1(
1:
04
05
1'
#60
16
0#
0)
0!
1;
12
1F
1=
07
0>
0.
0B
0(
1:
1*
11
1"
1E
14
15
0+
0,
0?
0@
0'
1&
#70
1#
0<
18
09
05
1'
